keywordlist/__init__.py
keywordlist/generator.py
keywordlist-1.0.0.dist-info/LICENSE
keywordlist-1.0.0.dist-info/METADATA
keywordlist-1.0.0.dist-info/WHEEL
keywordlist-1.0.0.dist-info/top_level.txt
keywordlist-1.0.0.dist-info/RECORD
